README.md
setup.py
jedi/__init__.py
jedi/__main__.py
jedi/_compatibility.py
jedi/cache.py
jedi/common.py
jedi/debug.py
jedi/file_io.py
jedi/parser_utils.py
jedi/settings.py
jedi/utils.py
jedi/api/__init__.py
jedi/api/classes.py
jedi/api/completion.py
jedi/api/completion_cache.py
jedi/api/environment.py
jedi/api/errors.py
jedi/api/exceptions.py
jedi/api/file_name.py
jedi/api/helpers.py
jedi/api/interpreter.py
jedi/api/keywords.py
jedi/api/project.py
jedi/api/replstartup.py
jedi/api/strings.py
jedi/api/refactoring/__init__.py
jedi/api/refactoring/extract.py
jedi/inference/__init__.py
jedi/inference/analysis.py
jedi/inference/arguments.py
jedi/inference/base_value.py
jedi/inference/cache.py
jedi/inference/context.py
jedi/inference/docstrings.py
jedi/inference/dynamic_params.py
jedi/inference/filters.py
jedi/inference/finder.py
jedi/inference/flow_analysis.py
jedi/inference/helpers.py
jedi/inference/imports.py
jedi/inference/lazy_value.py
jedi/inference/names.py
jedi/inference/param.py
jedi/inference/parser_cache.py
jedi/inference/recursion.py
jedi/inference/references.py
jedi/inference/signature.py
jedi/inference/star_args.py
jedi/inference/syntax_tree.py
jedi/inference/sys_path.py
jedi/inference/utils.py
jedi/inference/compiled/__init__.py
jedi/inference/compiled/access.py
jedi/inference/compiled/getattr_static.py
jedi/inference/compiled/mixed.py
jedi/inference/compiled/value.py
jedi/inference/compiled/subprocess/__init__.py
jedi/inference/compiled/subprocess/__main__.py
jedi/inference/compiled/subprocess/functions.py
jedi/inference/gradual/__init__.py
jedi/inference/gradual/annotation.py
jedi/inference/gradual/base.py
jedi/inference/gradual/conversion.py
jedi/inference/gradual/generics.py
jedi/inference/gradual/stub_value.py
jedi/inference/gradual/type_var.py
jedi/inference/gradual/typeshed.py
jedi/inference/gradual/typing.py
jedi/inference/gradual/utils.py
jedi/inference/value/__init__.py
jedi/inference/value/decorator.py
jedi/inference/value/dynamic_arrays.py
snb_node.egg-info/PKG-INFO
snb_node.egg-info/SOURCES.txt
snb_node.egg-info/dependency_links.txt
snb_node.egg-info/top_level.txt
