Metadata-Version: 2.1
Name: snb-node
Version: 1.5.2
Summary: smart-notebook node
Home-page: http://smartnotebook.tech/
Author: wang xin yi
Author-email: wangxinyi@smartnotebook.tech
